MANIFEST.in
README
__init__.py
__pkginfo__.py
entities.py
hooks.py
schema.py
setup.py
testutils.py
views.py
cubicweb_collaboration.egg-info/PKG-INFO
cubicweb_collaboration.egg-info/SOURCES.txt
cubicweb_collaboration.egg-info/dependency_links.txt
cubicweb_collaboration.egg-info/not-zip-safe
cubicweb_collaboration.egg-info/requires.txt
cubicweb_collaboration.egg-info/top_level.txt
i18n/en.po
i18n/es.po
i18n/fr.po
migration/1.0.0_Any.py
migration/postcreate.py
test/pytestconf.py
test/test_collaboration.py
test/unittest_collaboration.py
test/unittest_hooks.py
test/unittest_utils.py