Metadata-Version: 1.1
Name: cubicweb-collaboration
Version: 1.1.0
Summary: Cube for providing facilities for cooperative entity handling
Home-page: http://www.cubicweb.org/project/cubicweb-collaboration
Author: LOGILAB S.A. (Paris, FRANCE)
Author-email: contact@logilab.fr
License: LGPL
Platform: UNKNOWN
Classifier: Environment :: Web Environment
Classifier: Framework :: CubicWeb
Classifier: Programming Language :: Python
Classifier: Programming Language :: JavaScript
